README.md
setup.py
freee/__init__.py
freee/freee.py
python_freee_api.egg-info/PKG-INFO
python_freee_api.egg-info/SOURCES.txt
python_freee_api.egg-info/dependency_links.txt
python_freee_api.egg-info/requires.txt
python_freee_api.egg-info/top_level.txt