Metadata-Version: 1.1
Name: python-freee-api
Version: 0.3
Summary: Python based freee api wrapper
Home-page: UNKNOWN
Author: Yuki Okada
Author-email: yuki.okada.1993@gmail.com
License: MIT
Keywords: python freee api wrapper
Platform: UNKNOWN
Classifier: Programming Language :: Python :: 3.6
